pyilastik/__init__.py
pyilastik/convert_ilp_to_tif.py
pyilastik/ilastik_storage_version_01.py
pyilastik/ilastik_version_05.py
pyilastik/lib.py
pyilastik/utils.py
pyilastik/tests/__init__.py
pyilastik/tests/test.py
pyilastik/tests/test_img_import.py
pyilastik/tests/test_label_import.py
pyilastik-0.0.2.dist-info/LICENSE
pyilastik-0.0.2.dist-info/METADATA
pyilastik-0.0.2.dist-info/WHEEL
pyilastik-0.0.2.dist-info/top_level.txt
pyilastik-0.0.2.dist-info/RECORD
