Metadata-Version: 2.1
Name: pyilastik
Version: 0.0.2
Summary: Read ilastik labels in python
Home-page: UNKNOWN
Author: Manuel Schoelling
Author-email: manuel.schoelling@dzne.de
License: UNKNOWN
Platform: UNKNOWN
Requires-Dist: h5py (>=2.6.0)
Requires-Dist: numpy (>=1.12.1)
Requires-Dist: docopt (>=0.6.2)
Requires-Dist: bigtiff (>=0.1.1)
